LICENSE
README.md
setup.cfg
setup.py
bin/uvn
bin/uvnd.profile
docs/man/uvn.1
docs/man/uvnd.profile.8
libuno/__init__.py
libuno/backbone.py
libuno/cell.py
libuno/cell_cfg.py
libuno/cfg.py
libuno/connext.py
libuno/deploy.py
libuno/docker.py
libuno/err.py
libuno/exception.py
libuno/exec.py
libuno/helpers.py
libuno/identity.py
libuno/install.py
libuno/ip.py
libuno/log.py
libuno/ns.py
libuno/particle.py
libuno/ping.py
libuno/psk.py
libuno/qr.py
libuno/reg.py
libuno/router_port.py
libuno/rs.py
libuno/strategy.py
libuno/tmplt.py
libuno/wg.py
libuno/www.py
libuno/www_api.py
libuno/yml.py
libuno.egg-info/PKG-INFO
libuno.egg-info/SOURCES.txt
libuno.egg-info/dependency_links.txt
libuno.egg-info/requires.txt
libuno.egg-info/top_level.txt
libuno/agent/__init__.py
libuno/agent/agent.py
libuno/agent/agent_cell.py
libuno/agent/agent_root.py
libuno/agent/dds.py
libuno/agent/dds_cell.py
libuno/agent/dds_root.py
libuno/agent/dds_rs.py
libuno/agent/peer.py
libuno/agent/peer_cb.py
libuno/agent/peer_manager.py
libuno/agent/proc.py
libuno/agent/publisher.py
libuno/agent/quagga.py
libuno/agent/router.py
libuno/agent/router_cell.py
libuno/agent/router_root.py
libuno/agent/vpn.py
libuno/agent/vpn_cell.py
libuno/agent/vpn_root.py
libuno/data/__init__.py
libuno/data/__pycache__/__init__.cpython-38.pyc
libuno/data/dds/__init__.py
libuno/data/dds/uno.rtisdproj
libuno/data/dds/uno.xml
libuno/data/dockerfiles/__init__.py
libuno/data/sh/__init__.py
libuno/data/sh/entrypoint.sh
libuno/data/www/__init__.py
libuno/data/www/css/__init__.py
libuno/gateway/__init__.py
libuno/gateway/gateway.py
libuno/templates/dds/rs-root.xml
libuno/templates/dds/rs.xml
libuno/templates/dns/address_db.conf
libuno/templates/dns/dnsmasq.conf
libuno/templates/dns/dnsmasq_bkp.conf
libuno/templates/dns/etc_hosts.conf
libuno/templates/dns/nameserver.conf
libuno/templates/dns/nameserver_db.conf
libuno/templates/dns/nameserver_hosts.conf
libuno/templates/dns/resolv.conf
libuno/templates/docker/Dockerfile
libuno/templates/md/deployment_report.md
libuno/templates/md/deployment_report_new.md
libuno/templates/particle/particle_manifest.md
libuno/templates/router/ospfd_cell.conf
