Metadata-Version: 2.1
Name: libuno
Version: 0.1.0
Summary: A library to implement the UNO virtual network
Home-page: https://uno.mentalsmash.org
Author: Andrea Sorbini
Author-email: uno@mentalsmash.org
License: License :: OSI Approved :: GNU Affero General Public License v3 or later (AGPLv3+)
Platform: UNKNOWN
Classifier: Development Status :: 3 - Alpha
Classifier: Programming Language :: Python :: 3
Classifier: License :: OSI Approved :: GNU Affero General Public License v3 or later (AGPLv3+)
Classifier: Operating System :: POSIX :: Linux
Requires-Python: >=3.6, <4
